{
    "key": "group_615985ebccb0a",
    "title": "Product",
    "fields": [],
    "location": [
        [
            {
                "param": "post_type",
                "operator": "==",
                "value": "product"
            }
        ]
    ],
    "menu_order": 0,
    "position": "acf_after_title",
    "style": "default",
    "label_placement": "top",
    "instruction_placement": "label",
    "hide_on_screen": "",
    "active": true,
    "description": "",
    "modified": 1633367028
}